PiShiftPy.py
PiShiftPy-0.1.1.dist-info/DESCRIPTION.rst
PiShiftPy-0.1.1.dist-info/METADATA
PiShiftPy-0.1.1.dist-info/metadata.json
PiShiftPy-0.1.1.dist-info/pbr.json
PiShiftPy-0.1.1.dist-info/RECORD
PiShiftPy-0.1.1.dist-info/top_level.txt
PiShiftPy-0.1.1.dist-info/WHEEL
