Metadata-Version: 2.0
Name: PiShiftPy
Version: 0.1.1
Summary: Easily use 74HC595 and Other Shift registers with your Raspberry Pi
Home-page: https://github.com/shrikantpatnaik/PiShiftPy
Author: Shrikant Patnaik
Author-email: me@shrikantpatnaik.com
License: MIT
Platform: UNKNOWN
Classifier: Development Status :: 5 - Production/Stable
Classifier: Intended Audience :: Developers
Classifier: Natural Language :: English
Classifier: License :: OSI Approved :: MIT License
Classifier: Operating System :: OS Independent
Classifier: Programming Language :: Python
Classifier: Programming Language :: Python :: 2
Classifier: Programming Language :: Python :: 2.6
Classifier: Programming Language :: Python :: 2.7
Classifier: Programming Language :: Python :: 3
Classifier: Programming Language :: Python :: 3.3
Classifier: Topic :: Software Development :: Libraries :: Python Modules
